lu/__init__.py
lu/cli.py
lu/id.py
lu/io.py
lu/serializer.py
lu_python-0.0.9.dist-info/licenses/LICENSE
lu_python-0.0.9.dist-info/METADATA
lu_python-0.0.9.dist-info/WHEEL
lu_python-0.0.9.dist-info/entry_points.txt
lu_python-0.0.9.dist-info/top_level.txt
lu_python-0.0.9.dist-info/RECORD
