Metadata-Version: 2.4
Name: lu-python
Version: 0.0.9
Summary: vcr-style record/replay stubbing library for Python methods
Author: Jack Xu
License: MIT License
Keywords: testing,recording,fixtures
Classifier: License :: OSI Approved :: MIT License
Classifier: Programming Language :: Python :: 3
Classifier: Programming Language :: Python :: 3 :: Only
Classifier: Programming Language :: Python :: 3.10
Classifier: Intended Audience :: Developers
Classifier: Topic :: Software Development :: Testing
Requires-Python: >=3.9
License-File: LICENSE
Provides-Extra: zstd
Requires-Dist: zstandard>=0.21.0; extra == "zstd"
Provides-Extra: yaml
Requires-Dist: PyYAML>=6.0; extra == "yaml"
Provides-Extra: dev
Requires-Dist: pytest>=7.0; extra == "dev"
Requires-Dist: pytest-asyncio>=0.20; extra == "dev"
Requires-Dist: coverage; extra == "dev"
Requires-Dist: PyYAML>=6.0; extra == "dev"
Requires-Dist: flake8>=6.1; extra == "dev"
Dynamic: license-file
